goblet_gcp_client/__init__.py
goblet_gcp_client/__version__.py
goblet_gcp_client/client.py
goblet_gcp_client/http_files.py
goblet_gcp_client-0.1.9.dist-info/LICENSE
goblet_gcp_client-0.1.9.dist-info/METADATA
goblet_gcp_client-0.1.9.dist-info/WHEEL
goblet_gcp_client-0.1.9.dist-info/top_level.txt
goblet_gcp_client-0.1.9.dist-info/RECORD
