Metadata-Version: 2.1
Name: goblet-gcp-client
Version: 0.1.9
Summary: GCP Client and GCP integration testing helpers
Home-page: https://github.com/goblet/goblet_gcp_client
Author: Austen
Author-email: austen.novis@gmail.com
License: MIT
Classifier: License :: OSI Approved :: MIT License
Classifier: Programming Language :: Python
Classifier: Programming Language :: Python :: 3
Classifier: Programming Language :: Python :: 3.8
Classifier: Programming Language :: Python :: 3.9
Classifier: Programming Language :: Python :: 3.10
Classifier: Programming Language :: Python :: 3.11
Classifier: Programming Language :: Python :: Implementation :: CPython
Classifier: Programming Language :: Python :: Implementation :: PyPy
Requires-Python: >=3.8.0
License-File: LICENSE
Requires-Dist: google-api-python-client
Requires-Dist: six
